AUTHORS
COPYING
INSTALL
MANIFEST.in
README
conftest.py
dsutils.py
hgdistver.py
run-pida-remote.sh
run-pida.py
run-plugin-upload.py
setup.cfg
setup.py
bin/pida
bin/pida-build
bin/pida-remote
contrib/gtkrc/dark.gtkrc-2.0
contrib/moo/Makefile
contrib/moo/argtypes_m.py
contrib/moo/attach.png
contrib/moo/close.png
contrib/moo/detach.png
contrib/moo/hide.png
contrib/moo/keepontop.png
contrib/moo/marshals.c
contrib/moo/marshals.list
contrib/moo/moo-pygtk.c
contrib/moo/moo-stub.c
contrib/moo/moo.defs
contrib/moo/moo.override
contrib/moo/moobigpaned.c
contrib/moo/moobigpaned.h
contrib/moo/moopane.c
contrib/moo/moopane.h
contrib/moo/moopaned.c
contrib/moo/moopaned.defs
contrib/moo/moopaned.h
contrib/moo/moopaned.override
contrib/moo/moopython-utils.c
contrib/moo/moopython-utils.h
contrib/moo/mootype-macros.h
contrib/moo/sticky.png
contrib/moo/test.c
docs/Makefile
docs/README
docs/epydoc.conf
docs/source/conf.py
docs/source/index.rst
docs/source/links.rst
docs/source/_static/background.jpg
docs/source/_static/default.css
docs/source/_static/nav.jpg
docs/source/_static/pida-logo-tiny.png
docs/source/_static/pida-sidebar.jpg
docs/source/_templates/layout.html
docs/source/developer/coding_guideline.rst
docs/source/developer/codingstyle.rst
docs/source/developer/index.rst
docs/source/developer/introduction.rst
docs/source/developer/sourcecode.rst
docs/source/developer/service/commands.rst
docs/source/developer/service/components.rst
docs/source/developer/service/creating.rst
docs/source/developer/service/dbus.rst
docs/source/developer/service/events.rst
docs/source/developer/service/index.rst
docs/source/developer/service/options.rst
docs/source/developer/service/overview.rst
docs/source/developer/service/publishing.rst
docs/source/developer/service/views.rst
docs/source/user/about.rst
docs/source/user/emacs.rst
docs/source/user/gettingstarted.rst
docs/source/user/index.rst
docs/source/user/installation.rst
docs/source/user/introduction.rst
docs/source/user/missing_services.rst
pida.egg-info/PKG-INFO
pida.egg-info/SOURCES.txt
pida.egg-info/dependency_links.txt
pida.egg-info/requires.txt
pida.egg-info/top_level.txt
