Metadata-Version: 1.0
Name: pida
Version: 0.6.2
Summary: An integrated development environment that reuses tools such as Vim, and all version control systems.
Home-page: http://pida.co.uk/
Author: Ali Afshar <aafshar@gmail.com>
Author-email: Ali Afshar <aafshar@gmail.com>
License: GPL
Platform: UNKNOWN
Classifier: Development Status :: 4 - Beta
Classifier: Environment :: X11 Applications :: GTK
Classifier: Intended Audience :: Developers
Classifier: License :: OSI Approved :: GNU General Public License (GPL)
Classifier: Operating System :: POSIX :: Linux
Classifier: Operating System :: POSIX :: BSD
Classifier: Operating System :: Microsoft :: Windows :: Windows NT/2000
Classifier: Topic :: Software Development
Classifier: Topic :: Software Development :: Version Control
Classifier: Topic :: Text Editors
Classifier: Topic :: Text Editors :: Integrated Development Environments (IDE)
Classifier: Topic :: Text Editors :: Emacs
Classifier: Topic :: Utilities
Classifier: Programming Language :: Python
